atlasclient/__init__.py
atlasclient/base.py
atlasclient/client.py
atlasclient/data_types.py
atlasclient/events.py
atlasclient/exceptions.py
atlasclient/models.py
atlasclient/utils.py
atlasclient/glossary/__init__.py
atlasclient/glossary/data_types.py
atlasclient/glossary/endpoints.py
atlasclient/glossary/models.py
pyatlasclient-1.2.0.dist-info/AUTHORS.rst
pyatlasclient-1.2.0.dist-info/LICENSE
pyatlasclient-1.2.0.dist-info/METADATA
pyatlasclient-1.2.0.dist-info/WHEEL
pyatlasclient-1.2.0.dist-info/top_level.txt
pyatlasclient-1.2.0.dist-info/RECORD
