Metadata-Version: 2.1
Name: pyatlasclient
Version: 1.2.0
Summary: Apache Atlas Python Client
Home-page: https://github.com/verdan/pyatlasclient
Author: Verdan Mahmood
Author-email: verdan.mahmood@gmail.com
License: Apache Software License 2.0
Keywords: atlasclient,pyatlasclient,apache atlas,atlas
Platform: UNKNOWN
Classifier: Development Status :: 5 - Production/Stable
Classifier: Intended Audience :: Developers
Classifier: License :: OSI Approved :: Apache Software License
Classifier: Natural Language :: English
Classifier: Programming Language :: Python :: 3
Classifier: Programming Language :: Python :: 3.7
Classifier: Programming Language :: Python :: 3.8
License-File: LICENSE
License-File: AUTHORS.rst
Requires-Dist: six (>=1.11.0)
Requires-Dist: Click (>=6.0)
Requires-Dist: requests (>=2.18.4)
Requires-Dist: pydantic (>=1.7.2)
